kenchi/__init__.py
kenchi/metrics.py
kenchi/pipeline.py
kenchi/plotting.py
kenchi/utils.py
kenchi/datasets/__init__.py
kenchi/datasets/base.py
kenchi/datasets/samples_generator.py
kenchi/datasets/data/pendigits_test.csv.gz
kenchi/datasets/data/pendigits_train.csv.gz
kenchi/datasets/data/pima.csv.gz
kenchi/datasets/data/wilt_test.csv.gz
kenchi/datasets/data/wilt_train.csv.gz
kenchi/datasets/tests/__init__.py
kenchi/datasets/tests/test_base.py
kenchi/datasets/tests/test_samples_generator.py
kenchi/outlier_detection/__init__.py
kenchi/outlier_detection/angle_based.py
kenchi/outlier_detection/base.py
kenchi/outlier_detection/classification_based.py
kenchi/outlier_detection/clustering_based.py
kenchi/outlier_detection/density_based.py
kenchi/outlier_detection/distance_based.py
kenchi/outlier_detection/ensemble.py
kenchi/outlier_detection/reconstruction_based.py
kenchi/outlier_detection/statistical.py
kenchi/outlier_detection/tests/__init__.py
kenchi/outlier_detection/tests/test_angle_based.py
kenchi/outlier_detection/tests/test_classification_based.py
kenchi/outlier_detection/tests/test_cluster_based.py
kenchi/outlier_detection/tests/test_density_based.py
kenchi/outlier_detection/tests/test_distance_based.py
kenchi/outlier_detection/tests/test_ensemble.py
kenchi/outlier_detection/tests/test_reconstruction_based.py
kenchi/outlier_detection/tests/test_statistical.py
kenchi/tests/__init__.py
kenchi/tests/all_tests.py
kenchi/tests/common_tests.py
kenchi/tests/test_pipeline.py
kenchi/tests/test_plotting.py
kenchi-0.10.0.dist-info/METADATA
kenchi-0.10.0.dist-info/RECORD
kenchi-0.10.0.dist-info/WHEEL
kenchi-0.10.0.dist-info/top_level.txt
