Metadata-Version: 2.1
Name: kenchi
Version: 0.10.0
Summary: A set of python modules for anomaly detection
Home-page: http://kenchi.rtfd.io
Author: Kon
Author-email: kon.y.ohr.n+kenchi@gmail.com
License: BSD 3-Clause License
Platform: UNKNOWN
Requires-Python: >=3.6
Provides-Extra: develop
Requires-Dist: numpy (>=1.13.3)
Requires-Dist: scikit-learn (>=0.20.0)
Requires-Dist: scipy (>=0.19.1)
Provides-Extra: develop
Requires-Dist: matplotlib (>=2.1.2); extra == 'develop'
Requires-Dist: networkx (>=2.2); extra == 'develop'
